schemadisplay_magic/__init__.py
schemadisplay_magic/schemadisplay.py
sqlalchemy_schemadisplay/__init__.py
schemadisplay_magic-0.0.8.dist-info/LICENSE
schemadisplay_magic-0.0.8.dist-info/METADATA
schemadisplay_magic-0.0.8.dist-info/WHEEL
schemadisplay_magic-0.0.8.dist-info/top_level.txt
schemadisplay_magic-0.0.8.dist-info/RECORD
