Metadata-Version: 2.1
Name: schemadisplay-magic
Version: 0.0.8
Summary: Python package installation for ipython_magic_sqlalchemy_schemadisplay
Home-page: https://github.com/innovationOUtside/ipython_magic_sqlalchemy_schemadisplay
Author: Tony Hirst
Author-email: tony.hirst@open.ac.uk
License: MIT
License-File: LICENSE
Requires-Dist: pandas
Requires-Dist: sqlalchemy
Requires-Dist: pydot
Requires-Dist: graphviz
